groovemat/__init__.py
groovemat/__main__.py
groovemat/cli.py
groovemat/data.py
groovemat/matgl_loss.py
groovemat/model.py
groovemat/utils/__init__.py
groovemat/utils/normalizer.py
groovemat-0.9.1.dist-info/licenses/LICENSE
groovemat-0.9.1.dist-info/METADATA
groovemat-0.9.1.dist-info/WHEEL
groovemat-0.9.1.dist-info/entry_points.txt
groovemat-0.9.1.dist-info/top_level.txt
groovemat-0.9.1.dist-info/RECORD
